__init__.py
connector.py
sqlserverconnector-0.1.4.dist-info/METADATA
sqlserverconnector-0.1.4.dist-info/WHEEL
sqlserverconnector-0.1.4.dist-info/top_level.txt
sqlserverconnector-0.1.4.dist-info/RECORD
