Metadata-Version: 2.4
Name: sqlServerConnector
Version: 0.1.4
Summary: A custom SQL Server Connector for ETL processes with Pandas
Author-email: Nguyen Minh Son <nguyen.minhson1511@gmail.com>
Project-URL: Homepage, https://github.com/johnnyb1509/sqlServerConnector
Keywords: sql,etl,pandas,sqlalchemy
Classifier: Programming Language :: Python :: 3
Classifier: Operating System :: OS Independent
Requires-Python: >=3.8
Requires-Dist: pandas>=1.5.0
Requires-Dist: numpy
Requires-Dist: sqlalchemy>=2.0.0
Requires-Dist: pyodbc
Requires-Dist: pyyaml
Requires-Dist: loguru
Requires-Dist: jupyterlab
